resselector/__init__.py
resselector/resselector.py
resselector-0.13.0.dist-info/LICENSE
resselector-0.13.0.dist-info/METADATA
resselector-0.13.0.dist-info/WHEEL
resselector-0.13.0.dist-info/RECORD
