Metadata-Version: 2.1
Name: resselector
Version: 0.13.0
Summary: A package for doing great things!
License: Proprietary
Author: NSO
Requires-Python: >=3.10,<4.0
Classifier: License :: Other/Proprietary License
Classifier: Programming Language :: Python :: 3
Classifier: Programming Language :: Python :: 3.10
Classifier: Programming Language :: Python :: 3.11
Requires-Dist: numpy (>=2.2.3,<3.0.0)
Requires-Dist: twine (>=6.1.0,<7.0.0)
